posecamera/__init__.py
posecamera/cli.py
posecamera/modules/__init__.py
posecamera/modules/file_providers.py
posecamera/modules/hand_tracker.py
posecamera/modules/one_euro_filter.py
posecamera/modules/pose_tracker.py
posecamera-2.1.2.dist-info/LICENSE
posecamera-2.1.2.dist-info/METADATA
posecamera-2.1.2.dist-info/WHEEL
posecamera-2.1.2.dist-info/entry_points.txt
posecamera-2.1.2.dist-info/top_level.txt
posecamera-2.1.2.dist-info/RECORD
