Metadata-Version: 2.1
Name: posecamera
Version: 2.1.2
Summary: Realtime Human Pose Estimation
Home-page: https://github.com/Wonder-Tree/PoseCamera
Author: WonderTree
Author-email: hello@wondertree.co
License: Apache-2.0
Platform: UNKNOWN
Classifier: License :: OSI Approved :: Apache Software License
Classifier: Programming Language :: Python :: 3
Classifier: Programming Language :: Python :: 3.7
Classifier: Programming Language :: Python :: 3.8
Requires-Dist: opencv-python
Requires-Dist: wget
Requires-Dist: tensorflow
Requires-Dist: shapely
Requires-Dist: scipy
